[
  [
    {
      "ques": "The construction crew prepared the ________ for the building.",
      "ans": "site"
    },
    {
      "ques": "It's important to ________ the performance of the project.",
      "ans": "evaluate"
    },
    {
      "ques": "She deserves ________ for her hard work.",
      "ans": "credit"
    },
    {
      "ques": "They decided to ________ new safety measures.",
      "ans": "institute"
    },
    {
      "ques": "Where can I ________ a copy of that book?",
      "ans": "obtain"
    },
    {
      "ques": "He has been a ________ of this city for many years.",
      "ans": "resident"
    },
    {
      "ques": "She worked hard to ________ her goals.",
      "ans": "achieve"
    },
    {
      "ques": "Can you ________ me with this task?",
      "ans": "assist"
    },
    {
      "ques": "Education is a ________ concern for parents.",
      "ans": "primary"
    },
    {
      "ques": "You can use a calculator to ________ the total.",
      "ans": "compute"
    }
  ],
  [
    {
      "ques": "He was able to ________ the necessary permits.",
      "ans": "obtain"
    },
    {
      "ques": "We need to ________ the potential risks.",
      "ans": "evaluate"
    },
    {
      "ques": "The ________ of the neighborhood are friendly.",
      "ans": "resident"
    },
    {
      "ques": "This is the ideal ________ for the new store.",
      "ans": "site"
    },
    {
      "ques": "I'd like to give ________ to the entire team.",
      "ans": "credit"
    },
    {
      "ques": "He needed to ________ the complex equation.",
      "ans": "compute"
    },
    {
      "ques": "I'm here to ________ you in any way I can.",
      "ans": "assist"
    },
    {
      "ques": "It takes determination to ________ success.",
      "ans": "achieve"
    },
    {
      "ques": "The government plans to ________ new laws.",
      "ans": "institute"
    },
    {
      "ques": "The ________ goal is to improve public health.",
      "ans": "primary"
    }
  ],
  [
    {
      "ques": "The ________ focus should be on safety.",
      "ans": "primary"
    },
    {
      "ques": "You can earn extra ________ for your contributions.",
      "ans": "credit"
    },
    {
      "ques": "The program can quickly ________ large datasets.",
      "ans": "compute"
    },
    {
      "ques": "His friend offered to ________ him with his project.",
      "ans": "assist"
    },
    {
      "ques": "The archaeologists excavated the ancient ________.",
      "ans": "site"
    },
    {
      "ques": "The ________ of the building reported the issue.",
      "ans": "resident"
    },
    {
      "ques": "He will ________ the candidates for the job.",
      "ans": "evaluate"
    },
    {
      "ques": "The university will ________ a new research center.",
      "ans": "institute"
    },
    {
      "ques": "The team worked hard to ________ the data.",
      "ans": "obtain"
    },
    {
      "ques": "The team was able to ________ victory.",
      "ans": "achieve"
    }
  ],
  [
    {
      "ques": "The ________ responsibility lies with the government.",
      "ans": "primary"
    },
    {
      "ques": "The teacher will ________ the students' work.",
      "ans": "evaluate"
    },
    {
      "ques": "She is a legal ________ of the country.",
      "ans": "resident"
    },
    {
      "ques": "He ________ed a high level of expertise in his field.",
      "ans": "achieve"
    },
    {
      "ques": "It's challenging to ________ accurate information.",
      "ans": "obtain"
    },
    {
      "ques": "You'll need to ________ the final cost.",
      "ans": "compute"
    },
    {
      "ques": "Volunteers ________ed the victims of the disaster.",
      "ans": "assist"
    },
    {
      "ques": "He helped ________ changes in the organization.",
      "ans": "institute"
    },
    {
      "ques": "The company chose this ________ for its headquarters.",
      "ans": "site"
    },
    {
      "ques": "His success is to his ________.",
      "ans": "credit"
    }
  ],
  [
    {
      "ques": "He's skilled in ________ing mathematical problems.",
      "ans": "compute"
    },
    {
      "ques": "She managed to ________ a scholarship.",
      "ans": "obtain"
    },
    {
      "ques": "The teacher ________ed the students with their assignments.",
      "ans": "assist"
    },
    {
      "ques": "The ________ of the accident was investigated.",
      "ans": "site"
    },
    {
      "ques": "The president hopes to ________ economic reforms.",
      "ans": "institute"
    },
    {
      "ques": "Only ________s are allowed to park here.",
      "ans": "resident"
    },
    {
      "ques": "They will ________ the impact of the new policy.",
      "ans": "evaluate"
    },
    {
      "ques": "Their efforts helped them ________ their dreams.",
      "ans": "achieve"
    },
    {
      "ques": "The ________ concern is to meet the deadline.",
      "ans": "primary"
    },
    {
      "ques": "The company received ________ for its innovation.",
      "ans": "credit"
    }
  ]
]
