[
  [
    {
      "ques": "The indigenous _________ has lived here for centuries.",
      "ans": "tribe"
    },
    {
      "ques": "The wedding _________ was a beautiful tradition.",
      "ans": "ritual"
    },
    {
      "ques": "They believe in the existence of _________ life.",
      "ans": "alien"
    },
    {
      "ques": "Can you _________ me on what to do next?",
      "ans": "advise"
    },
    {
      "ques": "A loyal _________ can make a journey enjoyable.",
      "ans": "companion"
    },
    {
      "ques": "The temple is considered a _________ place.",
      "ans": "sacred"
    },
    {
      "ques": "He's an _________ professor at the university.",
      "ans": "associate"
    },
    {
      "ques": "Her _________ for music is evident in her performances.",
      "ans": "passion"
    },
    {
      "ques": "It's important to address and prevent workplace _________.",
      "ans": "harass"
    },
    {
      "ques": "Let me _________ you to my friend, Sarah.",
      "ans": "introduce"
    },
    {
      "ques": "He felt deeply hurt when his friend _________ him.",
      "ans": "betray"
    },
    {
      "ques": "He liked to _________ his younger siblings.",
      "ans": "tease"
    },
    {
      "ques": "He's a _________ musician and songwriter.",
      "ans": "fellow"
    },
    {
      "ques": "It's important to avoid _________s and prejudices.",
      "ans": "stereotype"
    }
  ],
  [
    {
      "ques": "She often seeks her friend's _________.",
      "ans": "advise"
    },
    {
      "ques": "He has a deep _________ for photography.",
      "ans": "passion"
    },
    {
      "ques": "The spy was accused of _________ing secrets.",
      "ans": "betray"
    },
    {
      "ques": "She's been my _________ for many years.",
      "ans": "companion"
    },
    {
      "ques": "She studied the customs of a remote _________.",
      "ans": "tribe"
    },
    {
      "ques": "They perform a _________ before every meal.",
      "ans": "ritual"
    },
    {
      "ques": "She reported the ongoing _________ment to HR.",
      "ans": "harass"
    },
    {
      "ques": "He will _________ a new concept in his lecture.",
      "ans": "introduce"
    },
    {
      "ques": "_________s can limit our understanding of others.",
      "ans": "stereotype"
    },
    {
      "ques": "The land is regarded as _________ by the indigenous people.",
      "ans": "sacred"
    },
    {
      "ques": "The film explores the encounter with an _________ species.",
      "ans": "alien"
    },
    {
      "ques": "She playfully _________ed her friend about the prank.",
      "ans": "tease"
    },
    {
      "ques": "She introduced me to her _________ artists.",
      "ans": "fellow"
    },
    {
      "ques": "I _________ that song with my childhood.",
      "ans": "associate"
    }
  ],
  [
    {
      "ques": "The _________s of their culture are rich and meaningful.",
      "ans": "ritual"
    },
    {
      "ques": "The kids often _________ each other in good fun.",
      "ans": "tease"
    },
    {
      "ques": "They adopted a dog to be their _________.",
      "ans": "companion"
    },
    {
      "ques": "Their _________ has a rich cultural heritage.",
      "ans": "tribe"
    },
    {
      "ques": "I need some _________ on this matter.",
      "ans": "advise"
    },
    {
      "ques": "He felt like an _________ in a foreign land.",
      "ans": "alien"
    },
    {
      "ques": "It's painful when someone you trust _________s you.",
      "ans": "betray"
    },
    {
      "ques": "They're _________ members of the research team.",
      "ans": "fellow"
    },
    {
      "ques": "Follow your _________ and pursue your dreams.",
      "ans": "passion"
    },
    {
      "ques": "Respecting their traditions is a _________ duty.",
      "ans": "sacred"
    },
    {
      "ques": "She challenged the _________s associated with her profession.",
      "ans": "stereotype"
    },
    {
      "ques": "She tends to _________ with successful people.",
      "ans": "associate"
    },
    {
      "ques": "Bullying and _________ment can have serious consequences.",
      "ans": "harass"
    },
    {
      "ques": "The host will _________ the guest speaker.",
      "ans": "introduce"
    }
  ],
  [
    {
      "ques": "He considered his cat as a faithful _________.",
      "ans": "companion"
    },
    {
      "ques": "He's known for giving good _________.",
      "ans": "advise"
    },
    {
      "ques": "He would _________ her with a mischievous smile.",
      "ans": "tease"
    },
    {
      "ques": "Their shared _________ for art brought them together.",
      "ans": "passion"
    },
    {
      "ques": "The ceremony followed ancient _________s.",
      "ans": "ritual"
    },
    {
      "ques": "His actions seemed to _________ his true intentions.",
      "ans": "betray"
    },
    {
      "ques": "They hold _________ ceremonies in the forest.",
      "ans": "sacred"
    },
    {
      "ques": "He doesn't conform to the typical _________.",
      "ans": "stereotype"
    },
    {
      "ques": "The _________ has its own language and traditions.",
      "ans": "tribe"
    },
    {
      "ques": "He's a _________ traveler who loves adventures.",
      "ans": "fellow"
    },
    {
      "ques": "I don't _________ with that group anymore.",
      "ans": "associate"
    },
    {
      "ques": "She plans to _________ a new product next week.",
      "ans": "introduce"
    },
    {
      "ques": "Their customs seemed _________ to us.",
      "ans": "alien"
    },
    {
      "ques": "He faced constant _________ment from his classmates.",
      "ans": "harass"
    }
  ],
  [
    {
      "ques": "They all congratulated their _________ graduate.",
      "ans": "fellow"
    },
    {
      "ques": "The _________ text is revered by many.",
      "ans": "sacred"
    },
    {
      "ques": "Media often perpetuates harmful _________s.",
      "ans": "stereotype"
    },
    {
      "ques": "Having a _________ can ease loneliness.",
      "ans": "companion"
    },
    {
      "ques": "Members of the _________ gathered for a celebration.",
      "ans": "tribe"
    },
    {
      "ques": "They _________ his name with innovation.",
      "ans": "associate"
    },
    {
      "ques": "Participating in the _________ brought them closer.",
      "ans": "ritual"
    },
    {
      "ques": "His _________ for literature is inspiring.",
      "ans": "passion"
    },
    {
      "ques": "The teacher will _________ a new topic today.",
      "ans": "introduce"
    },
    {
      "ques": "It's all in good humor; they like to _________ each other.",
      "ans": "tease"
    },
    {
      "ques": "She couldn't believe he would _________ her like that.",
      "ans": "betray"
    },
    {
      "ques": "The organization has a zero-tolerance policy for _________.",
      "ans": "harass"
    },
    {
      "ques": "I would _________ against taking that route.",
      "ans": "advise"
    },
    {
      "ques": "The concept of time travel is often linked to _________ beings.",
      "ans": "alien"
    }
  ]
]
